lar/__init__.py
lar/executor.py
lar/formatter.py
lar/node.py
lar/spec/__init__.py
lar/spec/converters.py
lar/spec/linter.py
lar/spec/registry.py
lar/spec/spec.py
lar/state.py
lar/utils.py
lar_engine-1.0.1.dist-info/LICENSE
lar_engine-1.0.1.dist-info/METADATA
lar_engine-1.0.1.dist-info/NOTICE
lar_engine-1.0.1.dist-info/WHEEL
lar_engine-1.0.1.dist-info/RECORD
