Metadata-Version: 2.1
Name: lar-engine
Version: 1.0.1
Summary: Lár: The PyTorch for Agents. A 'define-by-run' agentic framework.
License: Apache-2.0
Author: Aadithya Vishnu Sajeev
Author-email: axdithya@snath.ai
Maintainer: Aadithya Vishnu Sajeev
Maintainer-email: axdithya@snath.ai
Requires-Python: >=3.11,<4.0
Classifier: License :: OSI Approved :: Apache Software License
Classifier: Programming Language :: Python :: 3
Classifier: Programming Language :: Python :: 3.11
Classifier: Programming Language :: Python :: 3.12
Requires-Dist: deepdiff (>=8.6.1,<9.0.0)
Requires-Dist: filelock (>=3.20.1,<4.0.0)
Requires-Dist: litellm (>=1.80.0,<2.0.0)
Requires-Dist: networkx (>=3.0.0,<4.0.0)
Requires-Dist: pydantic (>=2.0.0,<3.0.0)
Requires-Dist: rich (>=14.2.0,<15.0.0)
Requires-Dist: setuptools (>=78.0.0,<79.0.0)
Requires-Dist: urllib3 (>=2.6.0,<3.0.0)
